{
    "symbol": "Token Symbol",
    "account_name": "Apolinar Ramos",
    "overview": {
        "en": "COVID19",
        "zh": ""
    },
    "email": "rlapolinar68@gmail.com",
    "website": "https://your-awesome-project.com/",
    "whitepaper": "https://your-awesome-project.com/file.pdf",
    "published_on": "2018-01-01",
    "initial_price": {
        "EOS": "0.0016 EOS",
        "USD": "0.7 USD"
    },
    "links": {
        "steemit": "https://steemit.com/@your-awesome-project",
        "twitter": "https://twitter.com/polinaiz-awesome-project",
        "telegram": "https://t.me/joinchat/polinariz-awesome-project",
        "github": "https://github.com/lapolinar-mhlk-Task Inforcer",
        "reddit": "https://www.reddit.com/r/your-awesome-project/"
    }
}
